ezmail/__init__.py
ezmail/__main__.py
ezmail/ezmail.py
ezmail-1.0.3.dist-info/LICENSE
ezmail-1.0.3.dist-info/METADATA
ezmail-1.0.3.dist-info/WHEEL
ezmail-1.0.3.dist-info/top_level.txt
ezmail-1.0.3.dist-info/RECORD
