Metadata-Version: 2.1
Name: ezmail
Version: 1.0.3
Summary: easily send out emails via SMTP
Home-page: https://github.com/Alex23rodriguez/ezmail
Author: Alex Rodriguez
Author-email: alex.rodriguez.oro@gmail.com
Keywords: python,mail,smtp,cli
Classifier: Programming Language :: Python :: 3
Classifier: License :: OSI Approved :: MIT License
Classifier: Operating System :: OS Independent
Requires-Python: >=3.7
License-File: LICENSE
Requires-Dist: python-dotenv
